goatools/.gitignore
goatools/__init__.py
goatools/associations.py
goatools/base.py
goatools/evidence_codes.py
goatools/go_enrichment.py
goatools/go_search.py
goatools/godag_obosm.py
goatools/godag_plot.py
goatools/godag_small.py
goatools/mapslim.py
goatools/multiple_testing.py
goatools/nt_utils.py
goatools/obo_parser.py
goatools/obo_tasks.py
goatools/pvalcalc.py
goatools/randseed.py
goatools/ratio.py
goatools/semantic.py
goatools/statsdescribe.py
goatools/utils.py
goatools/version.py
goatools/wr_tbl.py
goatools/wr_tbl_class.py
goatools/anno/__init__.py
goatools/anno/annoreader_base.py
goatools/anno/broad_gos.py
goatools/anno/dnld_ebi_goa.py
goatools/anno/eco2group.py
goatools/anno/factory.py
goatools/anno/gaf_reader.py
goatools/anno/genetogo_reader.py
goatools/anno/gpad_reader.py
goatools/anno/idtogos_reader.py
goatools/anno/opts.py
goatools/anno/update_association.py
goatools/anno/extensions/__init__.py
goatools/anno/extensions/extension.py
goatools/anno/extensions/extensions.py
goatools/anno/extensions/factory.py
goatools/anno/init/__init__.py
goatools/anno/init/reader_gaf.py
goatools/anno/init/reader_genetogo.py
goatools/anno/init/reader_gpad.py
goatools/anno/init/reader_idtogos.py
goatools/anno/init/utils.py
goatools/cli/__init__.py
goatools/cli/compare_gos.py
goatools/cli/docopt_parse.py
goatools/cli/find_enrichment.py
goatools/cli/gos_get.py
goatools/cli/gosubdag_plot.py
goatools/cli/grouped.py
goatools/cli/ncbi_gene_results_to_python.py
goatools/cli/prt_terms.py
goatools/cli/wr_hierarchy.py
goatools/cli/wr_sections.py
goatools/godag/__init__.py
goatools/godag/consts.py
goatools/godag/go_tasks.py
goatools/godag/obo_optional_attributes.py
goatools/godag/prtfncs.py
goatools/godag/prttime.py
goatools/godag/relationship_combos.py
goatools/godag/relationship_str.py
goatools/godag/reldepth.py
goatools/godag/typedef.py
goatools/goea/__init__.py
goatools/goea/go_enrichment_ns.py
goatools/gosubdag/__init__.py
goatools/gosubdag/go_edges.py
goatools-1.5.2.dist-info/licenses/LICENSE
goatools-1.5.2.dist-info/METADATA
goatools-1.5.2.dist-info/WHEEL
goatools-1.5.2.dist-info/top_level.txt
goatools-1.5.2.dist-info/RECORD
