Metadata-Version: 2.4
Name: goatools
Version: 1.5.2
Summary: Python scripts to find enrichment of GO terms
Home-page: http://github.com/tanghaibao/goatools
Author: Haibao Tang, DV Klopfenstein
Author-email: tanghaibao@gmail.com
License: BSD
Classifier: Development Status :: 4 - Beta
Classifier: Intended Audience :: Science/Research
Classifier: License :: OSI Approved :: BSD License
Classifier: Programming Language :: Python
Classifier: Programming Language :: Python :: 2
Classifier: Programming Language :: Python :: 3
Classifier: Topic :: Scientific/Engineering :: Bio-Informatics
License-File: LICENSE
Requires-Dist: docopt-ng
Requires-Dist: ftpretty
Requires-Dist: numpy
Requires-Dist: openpyxl
Requires-Dist: pandas
Requires-Dist: pydot
Requires-Dist: requests
Requires-Dist: rich
Requires-Dist: scipy
Requires-Dist: setuptools
Requires-Dist: statsmodels
Requires-Dist: xlsxwriter
Dynamic: license-file
